[
    {
        "first": [
            {
                "title": "Almost Blue"
            },
            {
                "poster_link": "https://m.media-amazon.com/images/M/MV5BYWE1YzdkODktMjlmYy00ZTVjLTg4NzEtMTlhODY3OTIxYTJkXkEyXkFqcGdeQXVyMjQ5OTkwOTY@._V1_QL75_UX190_CR0,14,190,281_.jpg"
            },
            {
                "genres": [
                    "Short",
                    "Drama"
                ]
            },
            {
                "plot": "Add a plot in your language"
            },
            {
                "metascore": "1"
            }
        ]
    },
    {
        "actors": [
            {
                "image": null,
                "actor_name": "Daniel Goldfinch Betts",
                "character_name": "Alik"
            },
            {
                "image": null,
                "actor_name": "Jamie Richard-Stewart",
                "character_name": "Man"
            }
        ],
        "Director": [
            "Oscar Simmons"
        ],
        "Writer": [
            "Oscar Simmons"
        ],
        "All cast & crew": [],
        "Production, box office & more at IMDbPro": []
    },
    {
        "details": [
            {
                "title-details-releasedate": {
                    "val": [
                        "February 18, 2021 (United Kingdom)"
                    ],
                    "link": [
                        "/title/tt13893646/releaseinfo?ref_=tt_dt_rdat"
                    ]
                }
            },
            {
                "title-details-origin": {
                    "val": [
                        "United Kingdom"
                    ],
                    "link": [
                        "/search/title/?country_of_origin=GB&ref_=tt_dt_cn"
                    ]
                }
            },
            {
                "title-details-languages": {
                    "val": [
                        "English"
                    ],
                    "link": [
                        "/search/title?title_type=feature&primary_language=en&sort=moviemeter,asc&ref_=tt_dt_ln"
                    ]
                }
            },
            {
                "title-details-filminglocations": {
                    "val": [
                        "Edinburgh, Scotland, UK"
                    ],
                    "link": [
                        "/search/title?locations=Edinburgh%2C%20Scotland%2C%20UK&ref_=tt_dt_loc"
                    ]
                }
            }
        ]
    },
    {
        "boxOffice": [
            {
                "title-boxoffice-budget": {
                    "val": "\u00a31,000 (estimated)"
                }
            }
        ]
    },
    {
        "techspecs": [
            {
                "title-techspec_runtime": {
                    "val": "10 minutes"
                }
            },
            {
                "title-techspec_color": {
                    "val": [
                        "Color"
                    ]
                }
            }
        ]
    }
]