[
    {
        "first": [
            {
                "title": "Gholam"
            },
            {
                "poster_link": "https://m.media-amazon.com/images/M/MV5BNmFkM2UxYzgtY2EyNC00Mzc2LWI1M2ItODU1YmQ4NDU4Y2Q0XkEyXkFqcGdeQXVyNjY2OTM4MzM@._V1_QL75_UY281_CR127,0,190,281_.jpg"
            },
            {
                "genres": [
                    "Crime",
                    "Drama"
                ]
            },
            {
                "plot": "Haunted by his past and with an uncertain future, Gholam gets involved in the conflict of a total stranger and sees it through to the very end."
            },
            {
                "imdb-rating": "5.5/10"
            },
            {
                "metascore": "10"
            }
        ]
    },
    {
        "actors": [
            {
                "image": "https://m.media-amazon.com/images/M/MV5BZjVmZjNjMWUtYTRjMS00NDUwLWE1ZjctYzQ1NmUxYTY5MmUzXkEyXkFqcGdeQXVyMjQwMDg0Ng@@._V1_QL75_UX140_CR0,1,140,140_.jpg",
                "actor_name": "Shahab Hosseini",
                "character_name": "Gholam"
            },
            {
                "image": null,
                "actor_name": "Behrouz Behnejad",
                "character_name": "Mr. Sharif"
            },
            {
                "image": "https://m.media-amazon.com/images/M/MV5BZmExYTdkYjMtMjM0ZS00YmI1LWJjYjAtZDIzNDVjN2IwMzYxXkEyXkFqcGdeQXVyMjQwMDg0Ng@@._V1_QL75_UX140_CR0,0,140,140_.jpg",
                "actor_name": "Nasser Memarzia",
                "character_name": "The Quiet Man"
            },
            {
                "image": null,
                "actor_name": "Corinne Skinner-Carter",
                "character_name": "Mrs. Green"
            },
            {
                "image": null,
                "actor_name": "Colin Adrian",
                "character_name": "Producer in the taxi"
            },
            {
                "image": null,
                "actor_name": "Orson Nava",
                "character_name": "Security"
            },
            {
                "image": null,
                "actor_name": "Paolo Guglielmotti",
                "character_name": "Security"
            },
            {
                "image": null,
                "actor_name": "Philip Herbert",
                "character_name": "Cab office owner"
            },
            {
                "image": null,
                "actor_name": "Simin Sarkoob",
                "character_name": "Gholam's mother"
            },
            {
                "image": "https://m.media-amazon.com/images/M/MV5BNGU5NzM1OGItODMyMy00MGEwLWE0ZDEtNmM4NmJlMmM5NzRiXkEyXkFqcGdeQXVyNjg1MjQyMzg@._V1_QL75_UX140_CR0,0,140,140_.jpg",
                "actor_name": "Russell Parsi",
                "character_name": "Uncle"
            },
            {
                "image": null,
                "actor_name": "Soudabeh Neeya",
                "character_name": "Aunt"
            },
            {
                "image": null,
                "actor_name": "Mostafa Rajaai",
                "character_name": "Massoud"
            },
            {
                "image": "https://m.media-amazon.com/images/M/MV5BZmY3ZjU5OTAtNWRjOS00OWJkLWFlODctODczNjllNDc0NWI1XkEyXkFqcGdeQXVyNTk5NTEwOTg@._V1_QL75_UX140_CR0,0,140,140_.jpg",
                "actor_name": "Armin Karima",
                "character_name": "Arash"
            },
            {
                "image": null,
                "actor_name": "David Shackleton",
                "character_name": "Smoking man"
            },
            {
                "image": null,
                "actor_name": "Hossein Pakzad",
                "character_name": "Naive Man"
            },
            {
                "image": null,
                "actor_name": "Iman Bashari",
                "character_name": "News reader"
            },
            {
                "image": null,
                "actor_name": "Nahid Nazemi",
                "character_name": "Iranian woman passenger"
            },
            {
                "image": null,
                "actor_name": "Lee Long",
                "character_name": "Gang Leader"
            }
        ],
        "Director": [
            "Mitra Tabrizian"
        ],
        "Writers": [
            "Mitra Tabrizian",
            "Cyrus Massoudi"
        ],
        "All cast & crew": [],
        "Production, box office & more at IMDbPro": []
    },
    {
        "details": [
            {
                "title-details-releasedate": {
                    "val": [
                        "May 25, 2017 (United States)"
                    ],
                    "link": [
                        "/title/tt3511928/releaseinfo?ref_=tt_dt_rdat"
                    ]
                }
            },
            {
                "title-details-origin": {
                    "val": [
                        "United Kingdom",
                        "Iran"
                    ],
                    "link": [
                        "/search/title/?country_of_origin=GB&ref_=tt_dt_cn",
                        "/search/title/?country_of_origin=IR&ref_=tt_dt_cn"
                    ]
                }
            },
            {
                "details-officialsites": {
                    "val": [
                        "Official Site"
                    ],
                    "link": [
                        "http://gholamfilm.com/"
                    ]
                }
            },
            {
                "title-details-languages": {
                    "val": [
                        "English",
                        "Persian"
                    ],
                    "link": [
                        "/search/title?title_type=feature&primary_language=en&sort=moviemeter,asc&ref_=tt_dt_ln",
                        "/search/title?title_type=feature&primary_language=fa&sort=moviemeter,asc&ref_=tt_dt_ln"
                    ]
                }
            },
            {
                "title-details-filminglocations": {
                    "val": [
                        "London, England, UK"
                    ],
                    "link": [
                        "/search/title?locations=London%2C%20England%2C%20UK&ref_=tt_dt_loc"
                    ]
                }
            },
            {
                "title-details-companies": {
                    "val": [
                        "Aimimage Productions",
                        "Gholam"
                    ],
                    "link": [
                        "/company/co0103789?ref_=tt_dt_co_1",
                        "/company/co0743074?ref_=tt_dt_co_2"
                    ]
                }
            }
        ]
    },
    {
        "boxOffice": [
            {
                "title-boxoffice-cumulativeworldwidegross": {
                    "val": "$12,378"
                }
            }
        ]
    },
    {
        "techspecs": [
            {
                "title-techspec_runtime": {
                    "val": "1 hour 34 minutes"
                }
            },
            {
                "title-techspec_color": {
                    "val": [
                        "Color"
                    ]
                }
            },
            {
                "title-techspec_soundmix": {
                    "val": [
                        "Dolby Digital"
                    ]
                }
            },
            {
                "title-techspec_aspectratio": {
                    "val": [
                        "1.85 : 1"
                    ]
                }
            }
        ]
    }
]