[
    {
        "first": [
            {
                "title": "Ben & Eddie: Nightmare - Facing Fear"
            },
            {
                "genres": [
                    "Short",
                    "Family"
                ]
            },
            {
                "plot": "Add a plot in your language"
            }
        ]
    },
    {
        "actors": [],
        "Director": [
            "Joan F. Wood"
        ],
        "Writers": [
            "Camille Bonora",
            "Ben Harney"
        ],
        "All cast & crew": [],
        "Production, box office & more at IMDbPro": []
    },
    {
        "details": [
            {
                "title-details-releasedate": {
                    "val": [
                        "October 17, 1990 (United States)"
                    ],
                    "link": [
                        "/title/tt13187784/releaseinfo?ref_=tt_dt_rdat"
                    ]
                }
            },
            {
                "title-details-origin": {
                    "val": [
                        "United States"
                    ],
                    "link": [
                        "/search/title/?country_of_origin=US&ref_=tt_dt_cn"
                    ]
                }
            },
            {
                "title-details-languages": {
                    "val": [
                        "English"
                    ],
                    "link": [
                        "/search/title?title_type=feature&primary_language=en&sort=moviemeter,asc&ref_=tt_dt_ln"
                    ]
                }
            },
            {
                "title-details-companies": {
                    "val": [
                        "Great Pearl Communications"
                    ],
                    "link": [
                        "/company/co0822244?ref_=tt_dt_co_1"
                    ]
                }
            }
        ]
    },
    {
        "boxOffice": []
    },
    {
        "techspecs": [
            {
                "title-techspec_runtime": {
                    "val": "33 minutes"
                }
            },
            {
                "title-techspec_color": {
                    "val": [
                        "Color"
                    ]
                }
            }
        ]
    }
]