[
    {
        "first": [
            {
                "title": "Enough Sleep"
            },
            {
                "poster_link": "https://m.media-amazon.com/images/M/MV5BNDczMDBmMjgtNTAyOC00OWEyLTk0ZWMtZDFmNDc5Yjg5MmQzXkEyXkFqcGdeQXVyMTk5NzM2NDI@._V1_QL75_UX190_CR0,0,190,281_.jpg"
            },
            {
                "genres": [
                    "Short",
                    "Horror"
                ]
            },
            {
                "plot": "A woman encounters a series of surreal terrors while being kept awake by her crying baby."
            }
        ]
    },
    {
        "actors": [
            {
                "image": null,
                "actor_name": "Bryn Carter",
                "character_name": "Susan"
            },
            {
                "image": null,
                "actor_name": "Jason O'Connell",
                "character_name": "Jeff"
            },
            {
                "image": "https://m.media-amazon.com/images/M/MV5BMjE3Njg1NDEzN15BMl5BanBnXkFtZTcwNTk4Nzg5MQ@@._V1_QL75_UY140_CR2,0,140,140_.jpg",
                "actor_name": "Jeffrey Combs",
                "character_name": "Henry"
            },
            {
                "image": "https://m.media-amazon.com/images/M/MV5BMjA2MDYwNTEyMV5BMl5BanBnXkFtZTYwMzM3NDk1._V1_QL75_UX140_CR0,2,140,140_.jpg",
                "actor_name": "Sherilyn Fenn",
                "character_name": "Denise"
            },
            {
                "image": "https://m.media-amazon.com/images/M/MV5BNWVmNzlmYjEtYzIwNC00MWRmLWI5OTMtNjJhYTU4MzZkMzY5XkEyXkFqcGdeQXVyMzUwNTc1MTQ@._V1_QL75_UX140_CR0,1,140,140_.jpg",
                "actor_name": "Jo Walker",
                "character_name": "Courier"
            }
        ],
        "Director": [
            "Ben Botwick"
        ],
        "Writers": [
            "Ben Botwick",
            "Lizzie Minges"
        ],
        "All cast & crew": [],
        "Production, box office & more at IMDbPro": []
    },
    {
        "details": [
            {
                "title-details-releasedate": {
                    "val": [
                        "October 16, 2022 (United States)"
                    ],
                    "link": [
                        "/title/tt15046476/releaseinfo?ref_=tt_dt_rdat"
                    ]
                }
            },
            {
                "title-details-origin": {
                    "val": [
                        "United States"
                    ],
                    "link": [
                        "/search/title/?country_of_origin=US&ref_=tt_dt_cn"
                    ]
                }
            },
            {
                "details-officialsites": {
                    "val": [
                        "Mostmortem"
                    ],
                    "link": [
                        "https://www.mostmortem.com/"
                    ]
                }
            },
            {
                "title-details-languages": {
                    "val": [
                        "English"
                    ],
                    "link": [
                        "/search/title?title_type=feature&primary_language=en&sort=moviemeter,asc&ref_=tt_dt_ln"
                    ]
                }
            },
            {
                "title-details-companies": {
                    "val": [
                        "Mostmortem"
                    ],
                    "link": [
                        "/company/co0788286?ref_=tt_dt_co_1"
                    ]
                }
            }
        ]
    },
    {
        "boxOffice": []
    },
    {
        "techspecs": [
            {
                "title-techspec_runtime": {
                    "val": "19 minutes"
                }
            },
            {
                "title-techspec_color": {
                    "val": [
                        "Color"
                    ]
                }
            },
            {
                "title-techspec_aspectratio": {
                    "val": [
                        "16:9 HD"
                    ]
                }
            }
        ]
    }
]