[
    {
        "first": [
            {
                "title": ".in for Motion"
            },
            {
                "poster_link": "https://m.media-amazon.com/images/M/MV5BZjEyZjliM2ItMzQ3NC00NjA5LWE1M2YtYzlhZjI0MGEyMjFjXkEyXkFqcGdeQXVyMjM4MTU5MzE@._V1_QL75_UY281_CR5,0,190,281_.jpg"
            },
            {
                "genres": [
                    "Documentary"
                ]
            },
            {
                "plot": "A menagerie of miniscule human stories of changing India, from history of early computers to the myth of present IT bubble, both sides of development and progress."
            }
        ]
    },
    {
        "actors": []
    },
    {
        "details": [
            {
                "title-details-releasedate": {
                    "val": [
                        "November 21, 2008 (Netherlands)"
                    ],
                    "link": [
                        "/title/tt6605520/releaseinfo?ref_=tt_dt_rdat"
                    ]
                }
            },
            {
                "title-details-origin": {
                    "val": [
                        "India",
                        "Finland"
                    ],
                    "link": [
                        "/search/title/?country_of_origin=IN&ref_=tt_dt_cn",
                        "/search/title/?country_of_origin=FI&ref_=tt_dt_cn"
                    ]
                }
            },
            {
                "details-officialsites": {
                    "val": [
                        "Animagineer (India)"
                    ],
                    "link": [
                        "http://www.animagineer.com/in-for-motion/"
                    ]
                }
            },
            {
                "title-details-languages": {
                    "val": [
                        "English",
                        "Telugu",
                        "Hindi",
                        "Bengali"
                    ],
                    "link": [
                        "/search/title?title_type=feature&primary_language=en&sort=moviemeter,asc&ref_=tt_dt_ln",
                        "/search/title?title_type=feature&primary_language=te&sort=moviemeter,asc&ref_=tt_dt_ln",
                        "/search/title?title_type=feature&primary_language=hi&sort=moviemeter,asc&ref_=tt_dt_ln",
                        "/search/title?title_type=feature&primary_language=bn&sort=moviemeter,asc&ref_=tt_dt_ln"
                    ]
                }
            },
            {
                "title-details-companies": {
                    "val": [
                        "Animagineer",
                        "Yleisradio (YLE)",
                        "Stepsindia Technologies"
                    ],
                    "link": [
                        "/company/co0344836?ref_=tt_dt_co_1",
                        "/company/co0013526?ref_=tt_dt_co_2",
                        "/company/co0815735?ref_=tt_dt_co_3"
                    ]
                }
            }
        ]
    },
    {
        "boxOffice": [
            {
                "title-boxoffice-budget": {
                    "val": "\u20b93,200,000 (estimated)"
                }
            }
        ]
    },
    {
        "techspecs": [
            {
                "title-techspec_runtime": {
                    "val": "59 minutes"
                }
            },
            {
                "title-techspec_color": {
                    "val": [
                        "Color"
                    ]
                }
            },
            {
                "title-techspec_aspectratio": {
                    "val": [
                        "16:9 HD"
                    ]
                }
            }
        ]
    }
]