[
    {
        "first": [
            {
                "title": "Fixed"
            },
            {
                "poster_link": "https://m.media-amazon.com/images/M/MV5BZjY5ZGY2NzItMWVkYi00OTc4LTk0YTgtOGU0MDAxOGEwMjhjXkEyXkFqcGdeQXVyNjg0NzgwMTA@._V1_QL75_UY281_CR11,0,190,281_.jpg"
            },
            {
                "genres": [
                    "Short",
                    "Drama"
                ]
            },
            {
                "plot": "At a young man's repass, his loved ones are left to piece together the reasons for his sudden death."
            }
        ]
    },
    {
        "actors": [
            {
                "image": null,
                "actor_name": "Jennifer Ayo-Akinyemi",
                "character_name": "Geraldine"
            },
            {
                "image": null,
                "actor_name": "Jeremy Benson",
                "character_name": "Football Friend"
            },
            {
                "image": "https://m.media-amazon.com/images/M/MV5BYmRjOGZlMTQtMTY4Ny00M2VjLWE1N2ItZWZkODAxZmU3NDYxXkEyXkFqcGdeQXVyNDE5MjM5Mjg@._V1_QL75_UX140_CR0,12,140,140_.jpg",
                "actor_name": "Joy Brunson",
                "character_name": "Sharon"
            },
            {
                "image": "https://m.media-amazon.com/images/M/MV5BMTZiYzcyNGEtODY2OS00ZTk5LWIzYTAtMjQyNzA4MTVjYmE4XkEyXkFqcGdeQXVyNTEwNTg5MzE@._V1_QL75_UX140_CR0,12,140,140_.jpg",
                "actor_name": "Shannon Chappell",
                "character_name": "Jasmine"
            },
            {
                "image": "https://m.media-amazon.com/images/M/MV5BNzQ5YTgzMTQtNTJlMy00ODZmLTg5M2QtNWFiZDA1N2I1YTlkXkEyXkFqcGdeQXVyMjQwMDg0Ng@@._V1_QL75_UY140_CR6,0,140,140_.jpg",
                "actor_name": "Barika A. Croom",
                "character_name": "Tracy"
            },
            {
                "image": null,
                "actor_name": "Emmanuel Delu",
                "character_name": "Young James"
            },
            {
                "image": null,
                "actor_name": "Lauren Elliott",
                "character_name": "Grace"
            },
            {
                "image": null,
                "actor_name": "Russell Ellis Jr.",
                "character_name": "Guest 2"
            },
            {
                "image": null,
                "actor_name": "Porcha Evans",
                "character_name": "Guest 1"
            },
            {
                "image": null,
                "actor_name": "Kierra Herron",
                "character_name": "Couple with Baby"
            },
            {
                "image": null,
                "actor_name": "Booker Hinton",
                "character_name": "Henry"
            },
            {
                "image": null,
                "actor_name": "Rejet Hoard",
                "character_name": "Guest 4"
            },
            {
                "image": null,
                "actor_name": "Gina Jackson",
                "character_name": "Deena"
            },
            {
                "image": null,
                "actor_name": "Quiana Jeffries",
                "character_name": "Chef Q"
            },
            {
                "image": null,
                "actor_name": "Mark V. Jones",
                "character_name": "Pastor Tate"
            },
            {
                "image": "https://m.media-amazon.com/images/M/MV5BN2IyMTAyNzMtZDY3YS00Zjc4LThiYjktYWVhMDE2YTRiNjUzXkEyXkFqcGdeQXVyMjAxNjAxMTU@._V1_QL75_UX140_CR0,12,140,140_.jpg",
                "actor_name": "Leigha",
                "character_name": "Hazel"
            },
            {
                "image": "https://m.media-amazon.com/images/M/MV5BMDIyNzQ0OWEtMzkwMC00ODY5LThjNGUtZGE2ZjQ0M2Y2YTRjXkEyXkFqcGdeQXVyMjEwNjQ5MDA@._V1_QL75_UX140_CR0,12,140,140_.jpg",
                "actor_name": "Will Leon",
                "character_name": "Robert"
            },
            {
                "image": "https://m.media-amazon.com/images/M/MV5BNmYwYjQwYmItZjYwYS00OTZlLTk1OGYtYTI3ZTA0MTViOWM3XkEyXkFqcGdeQXVyMjA4MTQyODA@._V1_QL75_UX140_CR0,12,140,140_.jpg",
                "actor_name": "Doug Locke",
                "character_name": "Shane"
            }
        ],
        "Director": [
            "Ashley Ellis"
        ],
        "Writer": [
            "Porcha Evans"
        ],
        "All cast & crew": [],
        "Production, box office & more at IMDbPro": []
    },
    {
        "details": [
            {
                "title-details-releasedate": {
                    "val": [
                        "2014 (United States)"
                    ],
                    "link": [
                        "/title/tt3320454/releaseinfo?ref_=tt_dt_rdat"
                    ]
                }
            },
            {
                "title-details-origin": {
                    "val": [
                        "United States"
                    ],
                    "link": [
                        "/search/title/?country_of_origin=US&ref_=tt_dt_cn"
                    ]
                }
            },
            {
                "title-details-languages": {
                    "val": [
                        "English"
                    ],
                    "link": [
                        "/search/title?title_type=feature&primary_language=en&sort=moviemeter,asc&ref_=tt_dt_ln"
                    ]
                }
            },
            {
                "title-details-companies": {
                    "val": [
                        "Emerald City Arts"
                    ],
                    "link": [
                        "/company/co0454880?ref_=tt_dt_co_1"
                    ]
                }
            }
        ]
    },
    {
        "boxOffice": [
            {
                "title-boxoffice-budget": {
                    "val": "$10,000 (estimated)"
                }
            }
        ]
    },
    {
        "techspecs": [
            {
                "title-techspec_runtime": {
                    "val": "24 minutes"
                }
            },
            {
                "title-techspec_color": {
                    "val": [
                        "Color"
                    ]
                }
            }
        ]
    }
]