[
    {
        "first": [
            {
                "title": "The Red, Red Heart"
            },
            {
                "poster_link": "https://m.media-amazon.com/images/M/MV5BNDNmMzE1YWItMmY1My00ZTQ0LWJlZWEtZTQ1ZGQwMTQ1ODAxXkEyXkFqcGdeQXVyNjA5MTAzODY@._V1_QL75_UY281_CR89,0,190,281_.jpg"
            },
            {
                "genres": [
                    "Western"
                ]
            },
            {
                "plot": "Concerned about the failing health of Rhoda Tuttle, his fiancee, John DeWitt takes her to the lavish Arizona home of his friends, Jack and Katherine Newman. Although the Newmans try to cheer... Read all"
            }
        ]
    },
    {
        "actors": [
            {
                "image": "https://m.media-amazon.com/images/M/MV5BZWQ0YmJlMWUtNGNlOC00MzAwLThjMWMtZWMxMjUzNDk3MTFiXkEyXkFqcGdeQXVyMzI5NDcxNzI@._V1_QL75_UX140_CR0,8,140,140_.jpg",
                "actor_name": "Monroe Salisbury",
                "character_name": "Kut-le"
            },
            {
                "image": "https://m.media-amazon.com/images/M/MV5BMTkwOTQyOTczNV5BMl5BanBnXkFtZTcwNzEzMzMzOA@@._V1_QL75_UX140_CR0,0,140,140_.jpg",
                "actor_name": "Ruth Clifford",
                "character_name": "Rhoda Tuttle"
            },
            {
                "image": null,
                "actor_name": "Val Paul",
                "character_name": "Jack Newman"
            },
            {
                "image": "https://m.media-amazon.com/images/M/MV5BZjNkOTBiZjItZGU1OS00ZTI3LWExZWYtMzdlNGY3YzdiN2VhL2ltYWdlL2ltYWdlXkEyXkFqcGdeQXVyMzI5NDcxNzI@._V1_QL75_UX140_CR0,0,140,140_.jpg",
                "actor_name": "Gretchen Lederer",
                "character_name": "Katherine Newman"
            },
            {
                "image": null,
                "actor_name": "Allan Sears",
                "character_name": "John DeWitt"
            },
            {
                "image": "https://m.media-amazon.com/images/M/MV5BNzgwOGIyOWUtMzNhMi00NTA0LThkODItNTUzNDYwNWZhN2IyXkEyXkFqcGdeQXVyMDMxMjQwMw@@._V1_QL75_UY140_CR27,0,140,140_.jpg",
                "actor_name": "Monte Blue",
                "character_name": "Billy Porter"
            },
            {
                "image": "https://m.media-amazon.com/images/M/MV5BNTY2ZGExYjMtZDhkZi00ZjEwLWIzYjItYjM0ZGY3NzBhNTNiL2ltYWdlXkEyXkFqcGdeQXVyMzI5NDcxNzI@._V1_QL75_UX140_CR0,1,140,140_.jpg",
                "actor_name": "Neola May",
                "character_name": "Molly"
            }
        ],
        "Director": [
            "Wilfred Lucas"
        ],
        "Writers": [
            "Bess Meredyth",
            "Honore Morrow"
        ],
        "All cast & crew": [],
        "Production, box office & more at IMDbPro": []
    },
    {
        "details": [
            {
                "title-details-releasedate": {
                    "val": [
                        "April 8, 1918 (United States)"
                    ],
                    "link": [
                        "/title/tt0009540/releaseinfo?ref_=tt_dt_rdat"
                    ]
                }
            },
            {
                "title-details-origin": {
                    "val": [
                        "United States"
                    ],
                    "link": [
                        "/search/title/?country_of_origin=US&ref_=tt_dt_cn"
                    ]
                }
            },
            {
                "title-details-languages": {
                    "val": [
                        "None",
                        "English"
                    ],
                    "link": [
                        "/search/title?title_type=feature&primary_language=zxx&sort=moviemeter,asc&ref_=tt_dt_ln",
                        "/search/title?title_type=feature&primary_language=en&sort=moviemeter,asc&ref_=tt_dt_ln"
                    ]
                }
            },
            {
                "title-details-akas": {
                    "val": [],
                    "link": []
                }
            },
            {
                "title-details-companies": {
                    "val": [
                        "Universal Film Manufacturing Company"
                    ],
                    "link": [
                        "/company/co0048238?ref_=tt_dt_co_1"
                    ]
                }
            }
        ]
    },
    {
        "boxOffice": []
    },
    {
        "techspecs": [
            {
                "title-techspec_runtime": {
                    "val": "50 minutes"
                }
            },
            {
                "title-techspec_color": {
                    "val": [
                        "Black and White"
                    ]
                }
            },
            {
                "title-techspec_soundmix": {
                    "val": [
                        "Silent"
                    ]
                }
            },
            {
                "title-techspec_aspectratio": {
                    "val": [
                        "1.33 : 1"
                    ]
                }
            }
        ]
    }
]