[
    {
        "first": [
            {
                "title": "Fable: Teeth of Beasts"
            },
            {
                "poster_link": "https://m.media-amazon.com/images/M/MV5BMTc1NzM3ODI3OV5BMl5BanBnXkFtZTcwNzA2NTk5Mw@@._V1_QL75_UY281_CR2,0,190,281_.jpg"
            },
            {
                "genres": [
                    "Action",
                    "Fantasy",
                    "Horror"
                ]
            },
            {
                "plot": "Lilith Noir is a hardboiled freelance enforcer for the shadow government that keeps watch over the city of Fable, a mythical realm that exists just beneath the surface of our awareness. When... Read all"
            },
            {
                "imdb-rating": "4.1/10"
            },
            {
                "metascore": "5"
            }
        ]
    },
    {
        "actors": [
            {
                "image": "https://m.media-amazon.com/images/M/MV5BMWMwZmY4NzAtMjA2Mi00MDlmLTg3YjItZDM4YzU4ZWM1M2ZlXkEyXkFqcGdeQXVyMTAwMzUyMzUy._V1_QL75_UX140_CR0,5,140,140_.jpg",
                "actor_name": "Melantha Blackthorne",
                "character_name": "Lilith Noir"
            },
            {
                "image": null,
                "actor_name": "Dale Denton",
                "character_name": "Gallu Demon"
            },
            {
                "image": "https://m.media-amazon.com/images/M/MV5BODBhMjk1YTUtOGNhNy00OWNjLWEyZTktMmM2NmMyMmY4OGI1XkEyXkFqcGdeQXVyMjQwMDg0Ng@@._V1_QL75_UY140_CR35,0,140,140_.jpg",
                "actor_name": "Jose Rosete",
                "character_name": "Vulcan"
            },
            {
                "image": "https://m.media-amazon.com/images/M/MV5BZjE2NTBkOWUtNzdkYi00ZmI5LWEwNjctNWIwYzg5MGQ0YjdmXkEyXkFqcGdeQXVyMTAzNzgwODAz._V1_QL75_UX140_CR0,0,140,140_.jpg",
                "actor_name": "Tara Alexis",
                "character_name": "Samantha Parsifal"
            },
            {
                "image": null,
                "actor_name": "Fiona Horne",
                "character_name": "Maggie Trader"
            },
            {
                "image": "https://m.media-amazon.com/images/M/MV5BZDk0NDhiYTgtZTcwOC00NDMxLWE2ZGUtNGZlNjFkNDU3MzdmXkEyXkFqcGdeQXVyMjQwMDg0Ng@@._V1_QL75_UX140_CR0,12,140,140_.jpg",
                "actor_name": "James Ray",
                "character_name": "Detective Mitchell"
            },
            {
                "image": null,
                "actor_name": "Kathleen Benner",
                "character_name": "The Spirit of Rage"
            },
            {
                "image": "https://m.media-amazon.com/images/M/MV5BY2ViZDYyODAtOWZiMi00YTg5LTgzZjYtYjBkOWQ4ZmE2ZGNkXkEyXkFqcGdeQXVyMTE2NzA0Ng@@._V1_QL75_UY140_CR55,0,140,140_.jpg",
                "actor_name": "Seregon O'Dassey",
                "character_name": "The Crone"
            },
            {
                "image": "https://m.media-amazon.com/images/M/MV5BNWNkYWU3MTYtYWJlOS00MzYxLWJhODItNGU5YzllNjI5YjZiXkEyXkFqcGdeQXVyNjYwMzY5Mw@@._V1_QL75_UY140_CR35,0,140,140_.jpg",
                "actor_name": "Raw Leiba",
                "character_name": "Darius"
            },
            {
                "image": "https://m.media-amazon.com/images/M/MV5BMzRmNTJjMjktNmNlNC00NDk0LWJiZGMtYmYwNDBiZjYzOWNhXkEyXkFqcGdeQXVyMjQwMDg0Ng@@._V1_QL75_UX140_CR0,0,140,140_.jpg",
                "actor_name": "Tim O'Hearn",
                "character_name": "Hern the Hunter"
            },
            {
                "image": null,
                "actor_name": "M.D. Graham",
                "character_name": "Tower CEO"
            },
            {
                "image": null,
                "actor_name": "Cedric Sun",
                "character_name": "Sun-Yi"
            },
            {
                "image": null,
                "actor_name": "Alexander S. McBryde",
                "character_name": "Jean Paul"
            },
            {
                "image": null,
                "actor_name": "Manuel Psychos",
                "character_name": "Braux"
            },
            {
                "image": null,
                "actor_name": "Jess Weber",
                "character_name": "Gordon"
            },
            {
                "image": "https://m.media-amazon.com/images/M/MV5BYmVjYWFmMTMtNGQ0ZS00NzM4LWE1NGYtNzRhMzg4NDA5ZmNlXkEyXkFqcGdeQXVyNTcxMzExMg@@._V1_QL75_UY140_CR60,0,140,140_.jpg",
                "actor_name": "Aaron Krygier",
                "character_name": "The Minotaur"
            },
            {
                "image": null,
                "actor_name": "Lacey Flatt",
                "character_name": "Sidhe"
            },
            {
                "image": null,
                "actor_name": "Ralph Randolph",
                "character_name": "Father"
            }
        ],
        "Director": [
            "Sean-Michael Argo"
        ],
        "Writers": [
            "David R. Williams",
            "Matt Yeager",
            "Sean-Michael Argo"
        ],
        "All cast & crew": [],
        "Production, box office & more at IMDbPro": []
    },
    {
        "details": [
            {
                "title-details-releasedate": {
                    "val": [
                        "July 2010 (Canada)"
                    ],
                    "link": [
                        "/title/tt1283962/releaseinfo?ref_=tt_dt_rdat"
                    ]
                }
            },
            {
                "title-details-origin": {
                    "val": [
                        "United States"
                    ],
                    "link": [
                        "/search/title/?country_of_origin=US&ref_=tt_dt_cn"
                    ]
                }
            },
            {
                "title-details-languages": {
                    "val": [
                        "English"
                    ],
                    "link": [
                        "/search/title?title_type=feature&primary_language=en&sort=moviemeter,asc&ref_=tt_dt_ln"
                    ]
                }
            },
            {
                "title-details-akas": {
                    "val": [],
                    "link": []
                }
            },
            {
                "title-details-companies": {
                    "val": [
                        "First Dark Productions"
                    ],
                    "link": [
                        "/company/co0246340?ref_=tt_dt_co_1"
                    ]
                }
            }
        ]
    },
    {
        "boxOffice": [
            {
                "title-boxoffice-budget": {
                    "val": "$50,000 (estimated)"
                }
            }
        ]
    },
    {
        "techspecs": [
            {
                "title-techspec_runtime": {
                    "val": "1 hour 47 minutes"
                }
            },
            {
                "title-techspec_color": {
                    "val": [
                        "Color"
                    ]
                }
            }
        ]
    }
]