[
    {
        "first": [
            {
                "title": "The Misunderstood Giant"
            },
            {
                "genres": [
                    "Animation",
                    "Short"
                ]
            },
            {
                "plot": "Beanstalk Jack is on trial for for crimes against Mr. and Mrs. Giant."
            }
        ]
    },
    {
        "actors": [],
        "Director": [
            "Connie Rasinski"
        ],
        "Writer": [
            "Larz Bourne"
        ],
        "All cast & crew": [],
        "Production, box office & more at IMDbPro": []
    },
    {
        "details": [
            {
                "title-details-releasedate": {
                    "val": [
                        "February 1960 (United States)"
                    ],
                    "link": [
                        "/title/tt0151598/releaseinfo?ref_=tt_dt_rdat"
                    ]
                }
            },
            {
                "title-details-origin": {
                    "val": [
                        "United States"
                    ],
                    "link": [
                        "/search/title/?country_of_origin=US&ref_=tt_dt_cn"
                    ]
                }
            },
            {
                "title-details-languages": {
                    "val": [
                        "English"
                    ],
                    "link": [
                        "/search/title?title_type=feature&primary_language=en&sort=moviemeter,asc&ref_=tt_dt_ln"
                    ]
                }
            },
            {
                "title-details-akas": {
                    "val": [],
                    "link": []
                }
            },
            {
                "title-details-companies": {
                    "val": [
                        "Terrytoons"
                    ],
                    "link": [
                        "/company/co0028853?ref_=tt_dt_co_1"
                    ]
                }
            }
        ]
    },
    {
        "boxOffice": []
    },
    {
        "techspecs": [
            {
                "title-techspec_runtime": {
                    "val": "7 minutes"
                }
            },
            {
                "title-techspec_aspectratio": {
                    "val": [
                        "2.35 : 1"
                    ]
                }
            }
        ]
    }
]