[
    {
        "first": [
            {
                "title": "Salt & Sauce"
            },
            {
                "poster_link": "https://m.media-amazon.com/images/M/MV5BNzhiMGMwYjktNWU1My00OWNmLWJhNWMtMmY1NmM3ZjdlZTMxXkEyXkFqcGdeQXVyNTg5ODE0Mjk@._V1_QL75_UY281_CR93,0,190,281_.jpg"
            },
            {
                "genres": [
                    "Short"
                ]
            },
            {
                "plot": "Stuck in a post high-school limbo, Tammy works long days in the family chip-shop. The only relief from the daily slog is her friendship with her colleague Jordan and her love for photography... Read all"
            },
            {
                "imdb-rating": "7.5/10"
            },
            {
                "metascore": "1"
            }
        ]
    },
    {
        "actors": [
            {
                "image": null,
                "actor_name": "Flora Bird",
                "character_name": "Tammy"
            }
        ],
        "Director": [
            "Alia Ghafar"
        ],
        "Writer": [
            "Alia Ghafar"
        ],
        "All cast & crew": [],
        "Production, box office & more at IMDbPro": []
    },
    {
        "details": [
            {
                "title-details-releasedate": {
                    "val": [
                        "October 8, 2017 (United Kingdom)"
                    ],
                    "link": [
                        "/title/tt7447404/releaseinfo?ref_=tt_dt_rdat"
                    ]
                }
            },
            {
                "title-details-origin": {
                    "val": [
                        "United Kingdom"
                    ],
                    "link": [
                        "/search/title/?country_of_origin=GB&ref_=tt_dt_cn"
                    ]
                }
            },
            {
                "details-officialsites": {
                    "val": [
                        "Official site"
                    ],
                    "link": [
                        "https://www.saltandsaucefilm.co.uk/"
                    ]
                }
            },
            {
                "title-details-languages": {
                    "val": [
                        "English"
                    ],
                    "link": [
                        "/search/title?title_type=feature&primary_language=en&sort=moviemeter,asc&ref_=tt_dt_ln"
                    ]
                }
            },
            {
                "title-details-filminglocations": {
                    "val": [
                        "North Queensferry, Fife, Scotland, UK"
                    ],
                    "link": [
                        "/search/title?locations=North%20Queensferry%2C%20Fife%2C%20Scotland%2C%20UK&ref_=tt_dt_loc"
                    ]
                }
            }
        ]
    },
    {
        "boxOffice": [
            {
                "title-boxoffice-budget": {
                    "val": "\u00a31,000 (estimated)"
                }
            }
        ]
    },
    {
        "techspecs": [
            {
                "title-techspec_runtime": {
                    "val": "11 minutes"
                }
            },
            {
                "title-techspec_color": {
                    "val": [
                        "Color"
                    ]
                }
            }
        ]
    }
]