[
    {
        "first": [
            {
                "title": "#Like"
            },
            {
                "poster_link": "https://m.media-amazon.com/images/M/MV5BYmNhOWQwNWYtNWNlZC00NjMyLTllYTMtNjY1OGQ4N2JiYTZiXkEyXkFqcGdeQXVyNTc2MTIzNw@@._V1_QL75_UY281_CR3,0,190,281_.jpg"
            },
            {
                "genres": [
                    "Thriller"
                ]
            },
            {
                "plot": "Rosie, mourning her younger sister's death discovers the mysterious man who sexploited and bullied her sister to commit suicide back online trolling for new victims, and she takes justice in... Read all"
            },
            {
                "imdb-rating": "4.7/10"
            },
            {
                "metascore": "54"
            }
        ]
    },
    {
        "actors": [
            {
                "image": "https://m.media-amazon.com/images/M/MV5BZTVhOTg1ZWMtNDVlMC00M2YwLThiZjMtMTgxOWU1ZTk4ZjQ3XkEyXkFqcGdeQXVyNDM5MjI4OA@@._V1_QL75_UX140_CR0,0,140,140_.jpg",
                "actor_name": "Marc Menchaca",
                "character_name": "The Man"
            },
            {
                "image": "https://m.media-amazon.com/images/M/MV5BMjg2ZjcwYjktNTkwNC00OGVhLTkwMmMtNWNlNDU0MzAxYTYzXkEyXkFqcGdeQXVyNjYwODk4Mg@@._V1_QL75_UY140_CR7,0,140,140_.jpg",
                "actor_name": "Jeff Wincott",
                "character_name": "Detective Horne"
            },
            {
                "image": "https://m.media-amazon.com/images/M/MV5BNWFlNGRjOGYtODRkNy00ODNkLWEwMGMtYTVmOGNmM2U5Y2IzXkEyXkFqcGdeQXVyMjc0OTM4OTk@._V1_QL75_UX140_CR0,12,140,140_.jpg",
                "actor_name": "Sarah Rich",
                "character_name": "Rosie"
            },
            {
                "image": "https://m.media-amazon.com/images/M/MV5BYjY2MjM1ZjItYjJlYS00YzMzLWFjNzQtZGYwZjA1YmJjNmZjXkEyXkFqcGdeQXVyOTgxODMxNA@@._V1_QL75_UX140_CR0,13,140,140_.jpg",
                "actor_name": "Dakota Lustick",
                "character_name": "Rory"
            },
            {
                "image": "https://m.media-amazon.com/images/M/MV5BZDI1MzI3YzctNTNmOC00ZGIxLWI4ZTktMGNjYTdhYThmMDRiXkEyXkFqcGdeQXVyNTY3NjMwMTQ@._V1_QL75_UX140_CR0,12,140,140_.jpg",
                "actor_name": "Ramon Nu\u00f1ez",
                "character_name": "Ray Boy"
            },
            {
                "image": "https://m.media-amazon.com/images/M/MV5BZTZhZTJmNjItNmFjNi00ZjJkLWJhNjctNGVlODIwMTE2YjBmXkEyXkFqcGdeQXVyNjQzMjkyMjg@._V1_QL75_UX140_CR0,12,140,140_.jpg",
                "actor_name": "Liz Meinders",
                "character_name": "D'rea"
            },
            {
                "image": "https://m.media-amazon.com/images/M/MV5BZWZjNTcxNmQtMTRiNS00ZDBhLWFkMWYtMTYzOTEwYzY4MGVjXkEyXkFqcGdeQXVyODUxNDIzNjg@._V1_QL75_UY140_CR35,0,140,140_.jpg",
                "actor_name": "Samantha Dunn",
                "character_name": "Amelia"
            },
            {
                "image": "https://m.media-amazon.com/images/M/MV5BZDUzZGJjYzYtNTFmYS00OTE0LTgwNTYtZTE2YmM3NTM3YmYwXkEyXkFqcGdeQXVyMjYyMzQxNDY@._V1_QL75_UY140_CR18,0,140,140_.jpg",
                "actor_name": "Jolene Marquez",
                "character_name": "Stacy"
            },
            {
                "image": "https://m.media-amazon.com/images/M/MV5BYTdlZmMzMWMtZWVkOS00MDM2LWI5ZTMtYWM4MGFiZTg4MGE1XkEyXkFqcGdeQXVyMzI1NTUxODA@._V1_QL75_UX140_CR0,0,140,140_.jpg",
                "actor_name": "Marin Gazzaniga",
                "character_name": "Melissa"
            }
        ],
        "Director": [
            "Sarah Pirozek"
        ],
        "Writer": [
            "Sarah Pirozek"
        ],
        "All cast & crew": [],
        "Production, box office & more at IMDbPro": []
    },
    {
        "details": [
            {
                "title-details-releasedate": {
                    "val": [
                        "July 1, 2020 (United States)"
                    ],
                    "link": [
                        "/title/tt5713856/releaseinfo?ref_=tt_dt_rdat"
                    ]
                }
            },
            {
                "title-details-origin": {
                    "val": [
                        "United States"
                    ],
                    "link": [
                        "/search/title/?country_of_origin=US&ref_=tt_dt_cn"
                    ]
                }
            },
            {
                "title-details-languages": {
                    "val": [
                        "English"
                    ],
                    "link": [
                        "/search/title?title_type=feature&primary_language=en&sort=moviemeter,asc&ref_=tt_dt_ln"
                    ]
                }
            },
            {
                "title-details-filminglocations": {
                    "val": [
                        "Woodstock, New York, USA"
                    ],
                    "link": [
                        "/search/title?locations=Woodstock%2C%20New%20York%2C%20USA&ref_=tt_dt_loc"
                    ]
                }
            },
            {
                "title-details-companies": {
                    "val": [
                        "DAME WORK Inc."
                    ],
                    "link": [
                        "/company/co0543166?ref_=tt_dt_co_1"
                    ]
                }
            }
        ]
    },
    {
        "boxOffice": []
    },
    {
        "techspecs": [
            {
                "title-techspec_runtime": {
                    "val": "1 hour 33 minutes"
                }
            },
            {
                "title-techspec_color": {
                    "val": [
                        "Color"
                    ]
                }
            }
        ]
    }
]